lamedec/__init__.py
lamedec/lamedec.py
lamedec/mp3reader.py
lamedec-0.1.2.dist-info/WHEEL
lamedec-0.1.2.dist-info/METADATA
lamedec-0.1.2.dist-info/RECORD
