Metadata-Version: 2.1
Name: lamedec
Version: 0.1.2
Summary: 
Home-page: https://github.com/sengokyu/python-lamedec
License: MIT
Author: sengokyu
Author-email: sengokyu+gh@gmail.com
Requires-Python: >=3.10,<4.0
Classifier: License :: OSI Approved :: MIT License
Classifier: Programming Language :: Python :: 3
Classifier: Programming Language :: Python :: 3.10
Requires-Dist: lame-ctypes (>=0.1.3,<0.2.0)
Project-URL: Repository, https://github.com/sengokyu/python-lamedec.git
